catmaid_publish/__init__.py
catmaid_publish/annotations.py
catmaid_publish/constants.py
catmaid_publish/initialise.py
catmaid_publish/io_helpers.py
catmaid_publish/landmarks.py
catmaid_publish/main.py
catmaid_publish/reader.py
catmaid_publish/skeletons.py
catmaid_publish/utils.py
catmaid_publish/version.py
catmaid_publish/volumes.py
catmaid_publish/package_data/README.md
catmaid_publish/package_data/config.toml
catmaid_publish/package_data/creds.env
catmaid_publish/package_data/creds.toml
catmaid_publish-0.1.0.dist-info/LICENSE
catmaid_publish-0.1.0.dist-info/METADATA
catmaid_publish-0.1.0.dist-info/WHEEL
catmaid_publish-0.1.0.dist-info/entry_points.txt
catmaid_publish-0.1.0.dist-info/top_level.txt
catmaid_publish-0.1.0.dist-info/RECORD
