Metadata-Version: 2.1
Name: catmaid-publish
Version: 0.1.0
Summary: Scripts for publishing data from CATMAID
Home-page: https://github.com/clbarnes/catmaid_publish
Author: Chris L. Barnes
Classifier: Programming Language :: Python :: 3
Requires-Python: >=3.9, <4.0
License-File: LICENSE
Requires-Dist: navis
Requires-Dist: python-catmaid (>=2.4)
Requires-Dist: meshio
Requires-Dist: pydantic
Requires-Dist: tomli-w
Requires-Dist: importlib-resources ; python_version < "3.10"
Requires-Dist: tomli ; python_version < "3.11"
Provides-Extra: dev
Requires-Dist: black ; extra == 'dev'
Requires-Dist: extreqs ; extra == 'dev'
Requires-Dist: flake8 ; extra == 'dev'
Requires-Dist: flake8-pyproject ; extra == 'dev'
Requires-Dist: ipdb ; extra == 'dev'
Requires-Dist: ipython ; extra == 'dev'
Requires-Dist: isort ; extra == 'dev'
Requires-Dist: mypy ; extra == 'dev'
Requires-Dist: pdoc3 ; extra == 'dev'
Requires-Dist: pipe2codeblock ; extra == 'dev'
Requires-Dist: pur ; extra == 'dev'
Requires-Dist: pytest ; extra == 'dev'
Requires-Dist: setuptools ; extra == 'dev'
Requires-Dist: setuptools-scm ; extra == 'dev'
Requires-Dist: wheel ; extra == 'dev'
